{
  "source": "https://scholar.google.com/citations?user=iD5b5lUAAAAJ&hl=en",
  "source_url": "https://scholar.google.com/citations?user=iD5b5lUAAAAJ&hl=en&cstart=0&pagesize=100",
  "updated_utc": "2026-07-20T12:00:08Z",
  "citations": {
    "safetyfirst": {
      "title": "CBF-Based Hierarchical Quadratic Programs With Guaranteed Feasibility for Safety-Critical Systems",
      "scholar_title": "CBF-Based Hierarchical Quadratic Programs With Guaranteed Feasibility for Safety-Critical Systems",
      "count": 12
    },
    "idmb": {
      "title": "Flexible and Safe Navigation of Autonomous Underwater Vehicles with Input-Dynamics Move Blocking",
      "scholar_title": "Flexible and Safe Navigation of Autonomous Underwater Vehicles with Input-Dynamics Move Blocking",
      "count": 2
    },
    "cac": {
      "title": "Certificated Actor-Critic: Hierarchical Reinforcement Learning with Control Barrier Functions for Safe Navigation",
      "scholar_title": "Certificated Actor-Critic: Hierarchical Reinforcement Learning with Control Barrier Functions for Safe Navigation",
      "count": 7
    }
  }
}
